connectrpc/__init__.py
connectrpc/call_options.py
connectrpc/client.py
connectrpc/client_interceptor.py
connectrpc/code.py
connectrpc/codec.py
connectrpc/compression.py
connectrpc/connect.py
connectrpc/connection_pool.py
connectrpc/content_stream.py
connectrpc/envelope.py
connectrpc/error.py
connectrpc/handler.py
connectrpc/handler_context.py
connectrpc/handler_interceptor.py
connectrpc/headers.py
connectrpc/idempotency_level.py
connectrpc/middleware.py
connectrpc/options.py
connectrpc/protocol.py
connectrpc/request.py
connectrpc/response.py
connectrpc/response_writer.py
connectrpc/utils.py
connectrpc/version.py
connectrpc/asgi_helpers/__init__.py
connectrpc/asgi_helpers/utils.py
connectrpc/protocol_connect/__init__.py
connectrpc/protocol_connect/base64_utils.py
connectrpc/protocol_connect/connect_client.py
connectrpc/protocol_connect/connect_handler.py
connectrpc/protocol_connect/connect_protocol.py
connectrpc/protocol_connect/constants.py
connectrpc/protocol_connect/content_type.py
connectrpc/protocol_connect/end_stream.py
connectrpc/protocol_connect/error_code.py
connectrpc/protocol_connect/error_json.py
connectrpc/protocol_connect/marshaler.py
connectrpc/protocol_connect/unmarshaler.py
connectrpc/protocol_grpc/__init__.py
connectrpc/protocol_grpc/constants.py
connectrpc/protocol_grpc/content_type.py
connectrpc/protocol_grpc/error_trailer.py
connectrpc/protocol_grpc/grpc_client.py
connectrpc/protocol_grpc/grpc_handler.py
connectrpc/protocol_grpc/grpc_protocol.py
connectrpc/protocol_grpc/marshaler.py
connectrpc/protocol_grpc/unmarshaler.py
connectrpc-0.0.1.dist-info/METADATA
connectrpc-0.0.1.dist-info/WHEEL
connectrpc-0.0.1.dist-info/licenses/LICENSE
connectrpc-0.0.1.dist-info/RECORD
